[{"title":"test","text":"test text","id":1},{"title":"hahjah","text":"hjha\n","id":2},{"title":"hahjah","text":"hjha\n","id":3},{"title":"hahjah","text":"hjha\n","id":4},{"title":"hahjah","text":"hjha\n","id":5},{"title":"hahjah","text":"hjha\n","id":6},{"title":"hahjah","text":"hjha\n","id":7},{"title":"jhgvhjb ","text":"jhvb kmn,. ","id":8},{"title":"jhgvhjb ","text":"jhvb kmn,. ","id":9},{"title":"jhgvhjb ","text":"jhvb kmn,. ","id":10},{"title":"jhgvhjb ","text":"jhvb kmn,. ","id":11},{"title":"jhgvhjb ","text":"jhvb kmn,. ","id":12},{"title":"jhgvhjb ","text":"jhvb kmn,. ","id":13},{"title":"jhgvhjb ","text":"jhvb kmn,. ","id":14},{"title":"jhgvhjb ","text":"jhvb kmn,. ","id":15},{"title":"ha nguyen","text":"Nguyen","id":16},{"title":"ha nguyen","text":"Nguyen","id":17}]